version_tagger.py
version_tagger-0.1.19.dist-info/METADATA
version_tagger-0.1.19.dist-info/WHEEL
version_tagger-0.1.19.dist-info/entry_points.txt
version_tagger-0.1.19.dist-info/licenses/LICENSE
version_tagger-0.1.19.dist-info/RECORD
