Metadata-Version: 2.4
Name: version-tagger
Version: 0.1.19
Summary: Add and bump semantic version tags to commits
Project-URL: Source, https://github.com/j-blackwell/version-tagger
Author-email: James Blackwell <33688964+j-blackwell@users.noreply.github.com>
License: MIT License
License-File: LICENSE
Classifier: Development Status :: 3 - Alpha
Classifier: Programming Language :: Python :: 3.10
Classifier: Programming Language :: Python :: 3.11
Classifier: Programming Language :: Python :: 3.12
Classifier: Programming Language :: Python :: 3.13
Requires-Python: <3.14,>=3.10
Requires-Dist: dunamai>=1.23.0
Requires-Dist: gitpython>=3.1.44
Requires-Dist: toml>=0.10.2
Requires-Dist: typer>=0.15.1
